mistral_extra/__init__.py
mistral_extra/config.py
mistral_extra/version.py
mistral_extra/workflows.py
mistral_extra/actions/__init__.py
mistral_extra/actions/action_generator.py
mistral_extra/actions/generator_factory.py
mistral_extra/actions/openstack/__init__.py
mistral_extra/actions/openstack/actions.py
mistral_extra/actions/openstack/base.py
mistral_extra/actions/openstack/mapping.json
mistral_extra/actions/openstack/action_generator/__init__.py
mistral_extra/actions/openstack/action_generator/base.py
mistral_extra/actions/openstack/utils/__init__.py
mistral_extra/actions/openstack/utils/context.py
mistral_extra/actions/openstack/utils/exceptions.py
mistral_extra/actions/openstack/utils/keystone.py
mistral_extra/monitoring/__init__.py
mistral_extra/monitoring/base.py
mistral_extra/monitoring/launch.py
mistral_extra/monitoring/monitoring_server.py
mistral_extra/monitoring/prometheus.py
mistral_extra/monitoring/collectors/__init__.py
mistral_extra/monitoring/collectors/mistral_collector.py
mistral_extra/monitoring/jobs/__init__.py
mistral_extra/monitoring/jobs/delayed_calls_recovery.py
mistral_extra/monitoring/jobs/idle_tasks_recovery.py
mistral_extra/monitoring/jobs/named_locks_recovery.py
mistral_extra/monitoring/jobs/subworkflow_complete_recovery.py
mistral_extra/monitoring/jobs/subworkflow_start_recovery.py
mistral_extra/monitoring/jobs/waiting_tasks_recovery.py
mistral_extra/resources/openstack/workflows/create_instance.yaml
mistral_extra/resources/openstack/workflows/delete_instance.yaml
mistral_extra/tests/__init__.py
mistral_extra/tests/resources/openstack/test_mapping.json
mistral_extra/tests/unit/__init__.py
mistral_extra/tests/unit/base.py
mistral_extra/tests/unit/test_base.py
mistral_extra/tests/unit/actions/__init__.py
mistral_extra/tests/unit/actions/openstack/__init__.py
mistral_extra/tests/unit/actions/openstack/test_generator.py
mistral_extra/tests/unit/actions/openstack/test_openstack_action_serialization.py
mistral_extra-16.0.0.dist-info/AUTHORS
mistral_extra-16.0.0.dist-info/LICENSE
mistral_extra-16.0.0.dist-info/METADATA
mistral_extra-16.0.0.dist-info/WHEEL
mistral_extra-16.0.0.dist-info/entry_points.txt
mistral_extra-16.0.0.dist-info/pbr.json
mistral_extra-16.0.0.dist-info/top_level.txt
mistral_extra-16.0.0.dist-info/RECORD
